{
  "collectionName": "components_navigation_sub_links",
  "info": {
    "displayName": "Sub Link",
    "description": "Secondary navigation link",
    "icon": "link"
  },
  "options": {},
  "attributes": {
    "label": {
      "type": "string",
      "required": true
    },
    "url": {
      "type": "string",
      "required": true
    },
    "openInNewTab": {
      "type": "boolean",
      "default": false
    },
    "isVisible": {
      "type": "boolean",
      "default": true
    },
    "ariaLabel": {
      "type": "string"
    }
  }
}
